tabman/__init__.py
tabman/categorizer.py
tabman/content_fetcher.py
tabman/main.py
tabman/tab_capture.py
tabman/tab_saver.py
tabman-0.4.0.dist-info/LICENSE
tabman-0.4.0.dist-info/METADATA
tabman-0.4.0.dist-info/WHEEL
tabman-0.4.0.dist-info/entry_points.txt
tabman-0.4.0.dist-info/top_level.txt
tabman-0.4.0.dist-info/RECORD
