Metadata-Version: 2.1
Name: tabman
Version: 0.4.0
Home-page: https://github.com/Anshulgada/brave-tab-manager
License-File: LICENSE
Requires-Dist: playwright
Requires-Dist: requests
Requires-Dist: beautifulsoup4
Requires-Dist: google-generativeai
Requires-Dist: google-api-python-client
Requires-Dist: tenacity
Requires-Dist: openai
Requires-Dist: python-dotenv
Requires-Dist: ollama
Requires-Dist: markdown
Requires-Dist: pytest-asyncio
